{
	"summary": "Update an existing option value",
	"operationId": "update-option-values",
	"tags": [
		{
			"$ref": "./../../tags/options.json#/name"
		}
	],
	"parameters": [
		{
			"name": "optionId",
			"in": "path",
			"description": "ID of an existing option.",
			"required": true,
			"style": "simple",
			"schema": {
				"type": "integer",
				"example": 1,
				"minimum": 1
			}
		}
	],
	"description": "Updates a single or multiple option values based on the request body.",
	"requestBody": {
		"description": "Option values data for update.",
		"required": true,
		"content": {
			"application/json": {
				"schema": {
					"$ref": "#/components/schemas/options-option-values-update"
				}
			}
		}
	},
	"responses": {
		"204": {
			"description": "Option values successfully updated.",
			"headers": {
				"X-Shop-Version": {
					"$ref": "#/components/headers/shopVersion"
				},
				"X-API-Version": {
					"$ref": "#/components/headers/apiVersion"
				},
				"X-Rate-Limit-Limit": {
					"$ref": "#/components/headers/rateLimitLimit"
				},
				"X-Rate-Limit-Remaining": {
					"$ref": "#/components/headers/rateLimitRemaining"
				},
				"X-Rate-Limit-Reset": {
					"$ref": "#/components/headers/rateLimitReset"
				}
			}
		},
		"400": {
			"$ref": "#/components/responses/missingAttribute"
		},
		"404": {
			"$ref": "#/components/responses/notFound"
		},
		"409": {
			"$ref": "#/components/responses/conflictByDataOrAction"
		},
		"422": {
			"$ref": "#/components/responses/invalidData"
		}
	}
}